odoo/addons/partner_type_membership/LICENSE
odoo/addons/partner_type_membership/README.rst
odoo/addons/partner_type_membership/__init__.py
odoo/addons/partner_type_membership/__manifest__.py
odoo/addons/partner_type_membership/i18n/de.po
odoo/addons/partner_type_membership/images/screen.png
odoo/addons/partner_type_membership/models/__init__.py
odoo/addons/partner_type_membership/models/res_partner.py
odoo/addons/partner_type_membership/static/description/icon.png
odoo/addons/partner_type_membership/static/description/index.html
odoo/addons/partner_type_membership/static/img/membership.png
odoo/addons/partner_type_membership/views/res_partner.xml
odoo_addon_partner_type_membership-18.0.1.0.0.dist-info/METADATA
odoo_addon_partner_type_membership-18.0.1.0.0.dist-info/WHEEL
odoo_addon_partner_type_membership-18.0.1.0.0.dist-info/top_level.txt
odoo_addon_partner_type_membership-18.0.1.0.0.dist-info/RECORD
